{"nodes": [{"id": "evaluation_evaluator_py", "label": "evaluator.py", "file_type": "code", "source_file": "evaluation/evaluator.py", "source_location": "L1"}, {"id": "evaluator_extract_label", "label": "extract_label()", "file_type": "code", "source_file": "evaluation/evaluator.py", "source_location": "L15"}, {"id": "evaluator_run_evaluation", "label": "run_evaluation()", "file_type": "code", "source_file": "evaluation/evaluator.py", "source_location": "L30"}, {"id": "evaluator_run_baseline2_majority_vote", "label": "run_baseline2_majority_vote()", "file_type": "code", "source_file": "evaluation/evaluator.py", "source_location": "L58"}, {"id": "evaluator_rationale_16", "label": "Extract the predicted threat category from the judge's final report.      Search", "file_type": "rationale", "source_file": "evaluation/evaluator.py", "source_location": "L16"}, {"id": "evaluator_rationale_31", "label": "Run the CyberCouncil pipeline on a labeled dataset and compute metrics.      Arg", "file_type": "rationale", "source_file": "evaluation/evaluator.py", "source_location": "L31"}], "edges": [{"source": "evaluation_evaluator_py", "target": "json", "relation": "imports", "confidence": "EXTRACTED", "source_file": "evaluation/evaluator.py", "source_location": "L1", "weight": 1.0}, {"source": "evaluation_evaluator_py", "target": "tqdm", "relation": "imports_from", "confidence": "EXTRACTED", "source_file": "evaluation/evaluator.py", "source_location": "L2", "weight": 1.0}, {"source": "evaluation_evaluator_py", "target": "council_orchestrator", "relation": "imports_from", "confidence": "EXTRACTED", "source_file": "evaluation/evaluator.py", "source_location": "L3", "weight": 1.0}, {"source": "evaluation_evaluator_py", "target": "evaluation_metrics", "relation": "imports_from", "confidence": "EXTRACTED", "source_file": "evaluation/evaluator.py", "source_location": "L4", "weight": 1.0}, {"source": "evaluation_evaluator_py", "target": "evaluator_extract_label", "relation": "contains", "confidence": "EXTRACTED", "source_file": "evaluation/evaluator.py", "source_location": "L15", "weight": 1.0}, {"source": "evaluation_evaluator_py", "target": "evaluator_run_evaluation", "relation": "contains", "confidence": "EXTRACTED", "source_file": "evaluation/evaluator.py", "source_location": "L30", "weight": 1.0}, {"source": "evaluation_evaluator_py", "target": "evaluator_run_baseline2_majority_vote", "relation": "contains", "confidence": "EXTRACTED", "source_file": "evaluation/evaluator.py", "source_location": "L58", "weight": 1.0}, {"source": "evaluator_run_evaluation", "target": "evaluator_extract_label", "relation": "calls", "confidence": "EXTRACTED", "source_file": "evaluation/evaluator.py", "source_location": "L50", "weight": 1.0}, {"source": "evaluator_run_baseline2_majority_vote", "target": "evaluator_extract_label", "relation": "calls", "confidence": "EXTRACTED", "source_file": "evaluation/evaluator.py", "source_location": "L71", "weight": 1.0}, {"source": "evaluator_rationale_16", "target": "evaluator_extract_label", "relation": "rationale_for", "confidence": "EXTRACTED", "source_file": "evaluation/evaluator.py", "source_location": "L16", "weight": 1.0}, {"source": "evaluator_rationale_31", "target": "evaluator_run_evaluation", "relation": "rationale_for", "confidence": "EXTRACTED", "source_file": "evaluation/evaluator.py", "source_location": "L31", "weight": 1.0}]}